pyderman/__init__.py
pyderman/py.typed
pyderman/drivers/__init__.py
pyderman/drivers/chrome.py
pyderman/drivers/edge.py
pyderman/drivers/firefox.py
pyderman/drivers/opera.py
pyderman/drivers/phantomjs.py
pyderman/util/__init__.py
pyderman/util/downloader.py
pyderman/util/github.py
pyderman-3.3.2.dist-info/LICENSE
pyderman-3.3.2.dist-info/METADATA
pyderman-3.3.2.dist-info/WHEEL
pyderman-3.3.2.dist-info/top_level.txt
pyderman-3.3.2.dist-info/RECORD
