Metadata-Version: 2.1
Name: pyderman
Version: 3.3.2
Summary: Installs the latest Chrome/Firefox/Opera/PhantomJS/Edge web drivers automatically.
Home-page: https://github.com/shadowmoose/pyderman
Author: ShadowMoose
Author-email: shadowmoose@github.com
License: MIT
Classifier: License :: OSI Approved :: MIT License
Classifier: Operating System :: OS Independent
Classifier: Programming Language :: Python :: 3
Classifier: Programming Language :: Python :: 3 :: Only
Classifier: Programming Language :: Python :: 3.7
Classifier: Programming Language :: Python :: 3.8
Classifier: Programming Language :: Python :: 3.9
Classifier: Programming Language :: Python :: 3.10
Requires-Python: >=3.7
Provides-Extra: dev
License-File: LICENSE
